tamnun/__init__.py
tamnun/bert/__init__.py
tamnun/bert/bert_classifier.py
tamnun/bert/bert_for_classification.py
tamnun/bert/bert_vectorizer.py
tamnun/bert/constants.py
tamnun/core/__init__.py
tamnun/core/torch_estimator.py
tamnun/transfer/__init__.py
tamnun/transfer/distiller.py
tamnun-0.1.1.dist-info/METADATA
tamnun-0.1.1.dist-info/WHEEL
tamnun-0.1.1.dist-info/top_level.txt
tamnun-0.1.1.dist-info/RECORD
