Metadata-Version: 2.1
Name: tamnun
Version: 0.1.1
Summary: An easy to use open-source library for advanced Deep Learning and Natural Language Processing
Home-page: https://github.com/hiredscorelabs/tamnun-ml
License: Apache
Keywords: Deep Learning Natural Language Processing NLP Machine Learning Transfer Learning
Platform: UNKNOWN
Requires-Dist: numpy (==1.15.4)
Requires-Dist: scikit-learn (==0.20.2)
Requires-Dist: torch (==1.1.0)
Requires-Dist: pytorch-transformers
